{"expireTime":9007200855570165000,"key":"create-remote-file-node-headers-https://dl.airtable.com/.attachments/0a2068b732f6675edabcaf5901677f45/03859271/DSC09984.JPG","val":{"content-type":"image/jpeg","content-length":"7354800","connection":"close","x-amz-replication-status":"COMPLETED","last-modified":"Mon, 21 Sep 2020 10:30:42 GMT","x-amz-server-side-encryption":"AES256","x-amz-version-id":"AL9HCw0.OcpJIl5pkBQ4MDiVB117CAeQ","accept-ranges":"bytes","server":"AmazonS3","content-security-policy":"default-src 'none'; style-src 'unsafe-inline'; img-src https://*/favicon.ico; sandbox","access-control-allow-origin":"*","x-robots-tag":"none","x-xss-protection":"1; mode=block","x-content-type-options":"nosniff","referrer-policy":"no-referrer","date":"Wed, 23 Sep 2020 02:46:07 GMT","etag":"\"a6b9700d0176b5bea0f6475923ab1ba3\"","x-cache":"RefreshHit from cloudfront","via":"1.1 7891adc32031b195876d8abd43962d02.cloudfront.net (CloudFront)","x-amz-cf-pop":"TPE51-C1","x-amz-cf-id":"8pWDBg8iTW9zVVTUxtSHJ9fT5568CGeASPrSvuQOfmxvNLxo-haj-A=="}}